sample/__init__.py
sample/package_data.dat
sample_test_101-1.2.0.data/data/my_data/data_file
sample_test_101-1.2.0.dist-info/DESCRIPTION.rst
sample_test_101-1.2.0.dist-info/METADATA
sample_test_101-1.2.0.dist-info/RECORD
sample_test_101-1.2.0.dist-info/WHEEL
sample_test_101-1.2.0.dist-info/entry_points.txt
sample_test_101-1.2.0.dist-info/metadata.json
sample_test_101-1.2.0.dist-info/top_level.txt
